flamewok/__init__.py
flamewok/cli.py
flamewok/cmd.py
flamewok/form.py
flamewok/helpers.py
flamewok/menu.py
flamewok/settings.py
flamewok/validators.py
flamewok/text/__init__.py
flamewok/text/color.py
flamewok/text/titles.py
flamewok/tools/__init__.py
flamewok/tools/json.py
flamewok-1.2.1.dist-info/LICENSE.md
flamewok-1.2.1.dist-info/METADATA
flamewok-1.2.1.dist-info/WHEEL
flamewok-1.2.1.dist-info/entry_points.txt
flamewok-1.2.1.dist-info/top_level.txt
flamewok-1.2.1.dist-info/RECORD
