Metadata-Version: 2.1
Name: flamewok
Version: 1.2.1
Summary: Python micro framework for terminal UI applications
Home-page: https://github.com/byoso/flamewok
Author: Vincent Fabre
Author-email: peigne.plume@gmail.com
License: MIT
Platform: UNKNOWN
Classifier: License :: OSI Approved :: MIT License
Classifier: Programming Language :: Python :: 3
Classifier: Development Status :: 5 - Production/Stable
Classifier: License :: OSI Approved :: MIT License
Classifier: Natural Language :: English
Classifier: Topic :: Software Development :: Libraries :: Application Frameworks
License-File: LICENSE.md
